[{"Name":"Jonathan Taylor","week":7.0,"FantasyPoints":21.69,"Team":"Trey"},{"Name":"David Montgomery","week":7.0,"FantasyPoints":10.02,"Team":"Trey"},{"Name":"James Cook","week":7.0,"FantasyPoints":6.09,"Team":"Trey"},{"Name":"Derrick Henry","week":7.0,"FantasyPoints":5.7,"Team":"Trey"},{"Name":"Kyler Murray","week":7.0,"FantasyPoints":14.36,"Team":"Trey"},{"Name":"Jordan Love","week":7.0,"FantasyPoints":16.3,"Team":"Trey"},{"Name":"C.J. Stroud","week":7.0,"FantasyPoints":17.39,"Team":"Trey"},{"Name":"CeeDee Lamb","week":7.0,"FantasyPoints":19.02,"Team":"Trey"},{"Name":"Deebo Samuel","week":7.0,"FantasyPoints":15.46,"Team":"Trey"},{"Name":"Garrett Wilson","week":7.0,"FantasyPoints":13.57,"Team":"Trey"},{"Name":"Courtland Sutton","week":7.0,"FantasyPoints":11.97,"Team":"Trey"},{"Name":"A.J. Brown","week":7.0,"FantasyPoints":8.54,"Team":"Trey"},{"Name":"Travis Hunter","week":7.0,"FantasyPoints":6.4,"Team":"Trey"},{"Name":"Harold Fannin","week":7.0,"FantasyPoints":11.99,"Team":"Trey"},{"Name":"Kyle Pitts","week":7.0,"FantasyPoints":9.45,"Team":"Trey"}]